{
  "updated_at": "2026-03-21T21:40:07.350900+00:00",
  "headline": {
    "title": "March Madness Pool Live Leaderboard",
    "subtitle": "Current standings and odds to win from the latest completed-game state."
  },
  "trend": {
    "baseline_updated_this_run": false,
    "current_completed_games": 34,
    "trend_reference_completed_games": 33,
    "latest_completed_game": "",
    "current_round_label": "Round of 32"
  },
  "summary_cards": [
    {
      "label": "Current Leader",
      "value": "Ellis Fleming",
      "detail": "41 points"
    },
    {
      "label": "Odds Favorite",
      "value": "Ellis Fleming",
      "detail": "15.6% win odds"
    },
    {
      "label": "Biggest Riser",
      "value": "Jack Reddeck",
      "detail": "7 rank spots"
    }
  ],
  "snapshot_state": {
    "current_snapshot_key": "beb794c701680ae0",
    "previous_snapshot_key": "642a0a38c44454af",
    "current_completed_games": 34,
    "previous_completed_games": 33,
    "trend_baseline_updated_this_run": false,
    "newly_completed_games_count": 0,
    "newly_completed_games": [],
    "latest_completed_game": "",
    "updated_at": "2026-03-21T21:40:07.350900+00:00"
  },
  "rows": [
    {
      "name": "Ellis Fleming",
      "current_rank": 1,
      "current_score": 41,
      "live_win_rate": 0.15581666666666666,
      "top4_rate": 0.4651499999999999,
      "remaining_live_teams": 10,
      "p50_score": 140.0,
      "best_case_score": 360,
      "top3_rate": 0.3835166666666667,
      "top10_rate": 0.7539166666666668,
      "last_rate": 0.0,
      "trend_rank_delta": 0.0,
      "trend_score_delta": 4.0,
      "trend_odds_delta": 0.022716666666666663,
      "trend_rank_direction": "flat",
      "current_rank_label": 1,
      "teams": [
        {
          "team": "Arizona",
          "alive": true,
          "current_round_status": "not_played_current_round"
        },
        {
          "team": "Illinois",
          "alive": true,
          "current_round_status": "not_played_current_round"
        },
        {
          "team": "Purdue",
          "alive": true,
          "current_round_status": "not_played_current_round"
        },
        {
          "team": "Tennessee",
          "alive": true,
          "current_round_status": "not_played_current_round"
        },
        {
          "team": "Vanderbilt",
          "alive": true,
          "current_round_status": "not_played_current_round"
        },
        {
          "team": "Michigan State",
          "alive": true,
          "current_round_status": "won_current_round"
        },
        {
          "team": "Arkansas",
          "alive": true,
          "current_round_status": "not_played_current_round"
        },
        {
          "team": "UCLA",
          "alive": true,
          "current_round_status": "not_played_current_round"
        },
        {
          "team": "Texas",
          "alive": true,
          "current_round_status": "not_played_current_round"
        },
        {
          "team": "Iowa State",
          "alive": true,
          "current_round_status": "not_played_current_round"
        }
      ]
    },
    {
      "name": "Stephen Mason",
      "current_rank": 2,
      "current_score": 40,
      "live_win_rate": 0.07031666666666667,
      "top4_rate": 0.22336666666666666,
      "remaining_live_teams": 9,
      "p50_score": 120.0,
      "best_case_score": 302,
      "top3_rate": 0.17960833333333331,
      "top10_rate": 0.4322466666666668,
      "last_rate": 0.00225,
      "trend_rank_delta": 0.0,
      "trend_score_delta": 4.0,
      "trend_odds_delta": 0.010316666666666668,
      "trend_rank_direction": "flat",
      "current_rank_label": 2,
      "teams": [
        {
          "team": "Michigan",
          "alive": true,
          "current_round_status": "won_current_round"
        },
        {
          "team": "Michigan State",
          "alive": true,
          "current_round_status": "won_current_round"
        },
        {
          "team": "Illinois",
          "alive": true,
          "current_round_status": "not_played_current_round"
        },
        {
          "team": "Kansas",
          "alive": true,
          "current_round_status": "not_played_current_round"
        },
        {
          "team": "Purdue",
          "alive": true,
          "current_round_status": "not_played_current_round"
        },
        {
          "team": "Vanderbilt",
          "alive": true,
          "current_round_status": "not_played_current_round"
        },
        {
          "team": "Wisconsin",
          "alive": false,
          "current_round_status": "eliminated_prior"
        },
        {
          "team": "Texas",
          "alive": true,
          "current_round_status": "not_played_current_round"
        },
        {
          "team": "Tennessee",
          "alive": true,
          "current_round_status": "not_played_current_round"
        },
        {
          "team": "Iowa",
          "alive": true,
          "current_round_status": "not_played_current_round"
        }
      ]
    },
    {
      "name": "Dan Downs",
      "current_rank": 3,
      "current_score": 38,
      "live_win_rate": 0.07488333333333333,
      "top4_rate": 0.2114166666666667,
      "remaining_live_teams": 10,
      "p50_score": 117.0,
      "best_case_score": 300,
      "top3_rate": 0.17375833333333332,
      "top10_rate": 0.4103266666666666,
      "last_rate": 0.0009333333333333332,
      "trend_rank_delta": 2.0,
      "trend_score_delta": 4.0,
      "trend_odds_delta": 0.010333333333333333,
      "trend_rank_direction": "up",
      "current_rank_label": 3,
      "teams": [
        {
          "team": "Duke",
          "alive": true,
          "current_round_status": "not_played_current_round"
        },
        {
          "team": "Kansas",
          "alive": true,
          "current_round_status": "not_played_current_round"
        },
        {
          "team": "Michigan State",
          "alive": true,
          "current_round_status": "won_current_round"
        },
        {
          "team": "Vanderbilt",
          "alive": true,
          "current_round_status": "not_played_current_round"
        },
        {
          "team": "Houston",
          "alive": true,
          "current_round_status": "not_played_current_round"
        },
        {
          "team": "Utah State",
          "alive": true,
          "current_round_status": "not_played_current_round"
        },
        {
          "team": "Texas Tech",
          "alive": true,
          "current_round_status": "not_played_current_round"
        },
        {
          "team": "Kentucky",
          "alive": true,
          "current_round_status": "not_played_current_round"
        },
        {
          "team": "Iowa State",
          "alive": true,
          "current_round_status": "not_played_current_round"
        },
        {
          "team": "Purdue",
          "alive": true,
          "current_round_status": "not_played_current_round"
        }
      ]
    },
    {
      "name": "Alec Piloto",
      "current_rank": 4,
      "current_score": 36,
      "live_win_rate": 0.02,
      "top4_rate": 0.16626666666666665,
      "remaining_live_teams": 9,
      "p50_score": 123.0,
      "best_case_score": 326,
      "top3_rate": 0.10938333333333335,
      "top10_rate": 0.4970433333333332,
      "last_rate": 0.0002,
      "trend_rank_delta": 6.0,
      "trend_score_delta": 4.0,
      "trend_odds_delta": 0.00255,
      "trend_rank_direction": "up",
      "current_rank_label": 4,
      "teams": [
        {
          "team": "Purdue",
          "alive": true,
          "current_round_status": "not_played_current_round"
        },
        {
          "team": "Arkansas",
          "alive": true,
          "current_round_status": "not_played_current_round"
        },
        {
          "team": "Arizona",
          "alive": true,
          "current_round_status": "not_played_current_round"
        },
        {
          "team": "Vanderbilt",
          "alive": true,
          "current_round_status": "not_played_current_round"
        },
        {
          "team": "North Carolina",
          "alive": false,
          "current_round_status": "eliminated_prior"
        },
        {
          "team": "Duke",
          "alive": true,
          "current_round_status": "not_played_current_round"
        },
        {
          "team": "UCLA",
          "alive": true,
          "current_round_status": "not_played_current_round"
        },
        {
          "team": "Michigan State",
          "alive": true,
          "current_round_status": "won_current_round"
        },
        {
          "team": "Tennessee",
          "alive": true,
          "current_round_status": "not_played_current_round"
        },
        {
          "team": "Texas Tech",
          "alive": true,
          "current_round_status": "not_played_current_round"
        }
      ]
    },
    {
      "name": "Nick Garas",
      "current_rank": 5,
      "current_score": 35,
      "live_win_rate": 0.1387,
      "top4_rate": 0.3882483333333334,
      "remaining_live_teams": 10,
      "p50_score": 138.0,
      "best_case_score": 297,
      "top3_rate": 0.3212366666666666,
      "top10_rate": 0.6967500000000002,
      "last_rate": 0.0,
      "trend_rank_delta": -2.0,
      "trend_score_delta": 0.0,
      "trend_odds_delta": -0.0020000000000000018,
      "trend_rank_direction": "down",
      "current_rank_label": 5,
      "teams": [
        {
          "team": "Purdue",
          "alive": true,
          "current_round_status": "not_played_current_round"
        },
        {
          "team": "Tennessee",
          "alive": true,
          "current_round_status": "not_played_current_round"
        },
        {
          "team": "Vanderbilt",
          "alive": true,
          "current_round_status": "not_played_current_round"
        },
        {
          "team": "Illinois",
          "alive": true,
          "current_round_status": "not_played_current_round"
        },
        {
          "team": "Arkansas",
          "alive": true,
          "current_round_status": "not_played_current_round"
        },
        {
          "team": "Gonzaga",
          "alive": true,
          "current_round_status": "not_played_current_round"
        },
        {
          "team": "Miami (FL)",
          "alive": true,
          "current_round_status": "not_played_current_round"
        },
        {
          "team": "Iowa State",
          "alive": true,
          "current_round_status": "not_played_current_round"
        },
        {
          "team": "Duke",
          "alive": true,
          "current_round_status": "not_played_current_round"
        },
        {
          "team": "Michigan",
          "alive": true,
          "current_round_status": "won_current_round"
        }
      ]
    },
    {
      "name": "Sid Cash Sr.",
      "current_rank": 5,
      "current_score": 35,
      "live_win_rate": 0.07941666666666666,
      "top4_rate": 0.23577499999999996,
      "remaining_live_teams": 10,
      "p50_score": 119.0,
      "best_case_score": 323,
      "top3_rate": 0.19213333333333335,
      "top10_rate": 0.44687333333333334,
      "last_rate": 0.0002,
      "trend_rank_delta": -2.0,
      "trend_score_delta": 0.0,
      "trend_odds_delta": 0.0015333333333333588,
      "trend_rank_direction": "down",
      "current_rank_label": 5,
      "teams": [
        {
          "team": "Duke",
          "alive": true,
          "current_round_status": "not_played_current_round"
        },
        {
          "team": "St. John's",
          "alive": true,
          "current_round_status": "not_played_current_round"
        },
        {
          "team": "UCLA",
          "alive": true,
          "current_round_status": "not_played_current_round"
        },
        {
          "team": "Utah State",
          "alive": true,
          "current_round_status": "not_played_current_round"
        },
        {
          "team": "Arkansas",
          "alive": true,
          "current_round_status": "not_played_current_round"
        },
        {
          "team": "Gonzaga",
          "alive": true,
          "current_round_status": "not_played_current_round"
        },
        {
          "team": "Vanderbilt",
          "alive": true,
          "current_round_status": "not_played_current_round"
        },
        {
          "team": "Houston",
          "alive": true,
          "current_round_status": "not_played_current_round"
        },
        {
          "team": "Texas Tech",
          "alive": true,
          "current_round_status": "not_played_current_round"
        },
        {
          "team": "Iowa State",
          "alive": true,
          "current_round_status": "not_played_current_round"
        }
      ]
    },
    {
      "name": "Frank Greer",
      "current_rank": 5,
      "current_score": 35,
      "live_win_rate": 0.06871666666666668,
      "top4_rate": 0.2400733333333333,
      "remaining_live_teams": 10,
      "p50_score": 126.0,
      "best_case_score": 280,
      "top3_rate": 0.18810333333333332,
      "top10_rate": 0.5003933333333335,
      "last_rate": 0.0,
      "trend_rank_delta": 6.0,
      "trend_score_delta": 4.0,
      "trend_odds_delta": 0.00903333333333338,
      "trend_rank_direction": "up",
      "current_rank_label": 5,
      "teams": [
        {
          "team": "Arkansas",
          "alive": true,
          "current_round_status": "not_played_current_round"
        },
        {
          "team": "Virginia",
          "alive": true,
          "current_round_status": "not_played_current_round"
        },
        {
          "team": "St. John's",
          "alive": true,
          "current_round_status": "not_played_current_round"
        },
        {
          "team": "Vanderbilt",
          "alive": true,
          "current_round_status": "not_played_current_round"
        },
        {
          "team": "Purdue",
          "alive": true,
          "current_round_status": "not_played_current_round"
        },
        {
          "team": "Nebraska",
          "alive": true,
          "current_round_status": "not_played_current_round"
        },
        {
          "team": "Gonzaga",
          "alive": true,
          "current_round_status": "not_played_current_round"
        },
        {
          "team": "Texas Tech",
          "alive": true,
          "current_round_status": "not_played_current_round"
        },
        {
          "team": "Michigan State",
          "alive": true,
          "current_round_status": "won_current_round"
        },
        {
          "team": "Arizona",
          "alive": true,
          "current_round_status": "not_played_current_round"
        }
      ]
    },
    {
      "name": "Ben Hewitt",
      "current_rank": 5,
      "current_score": 35,
      "live_win_rate": 0.059433333333333324,
      "top4_rate": 0.18894833333333333,
      "remaining_live_teams": 10,
      "p50_score": 108.0,
      "best_case_score": 288,
      "top3_rate": 0.15332,
      "top10_rate": 0.35178333333333334,
      "last_rate": 0.00065,
      "trend_rank_delta": 6.0,
      "trend_score_delta": 4.0,
      "trend_odds_delta": 0.0057000000000000245,
      "trend_rank_direction": "up",
      "current_rank_label": 5,
      "teams": [
        {
          "team": "Michigan",
          "alive": true,
          "current_round_status": "won_current_round"
        },
        {
          "team": "Iowa State",
          "alive": true,
          "current_round_status": "not_played_current_round"
        },
        {
          "team": "Vanderbilt",
          "alive": true,
          "current_round_status": "not_played_current_round"
        },
        {
          "team": "Miami (FL)",
          "alive": true,
          "current_round_status": "not_played_current_round"
        },
        {
          "team": "Gonzaga",
          "alive": true,
          "current_round_status": "not_played_current_round"
        },
        {
          "team": "Michigan State",
          "alive": true,
          "current_round_status": "won_current_round"
        },
        {
          "team": "UConn",
          "alive": true,
          "current_round_status": "not_played_current_round"
        },
        {
          "team": "Houston",
          "alive": true,
          "current_round_status": "not_played_current_round"
        },
        {
          "team": "Nebraska",
          "alive": true,
          "current_round_status": "not_played_current_round"
        },
        {
          "team": "Texas Tech",
          "alive": true,
          "current_round_status": "not_played_current_round"
        }
      ]
    },
    {
      "name": "Cole Dalton",
      "current_rank": 9,
      "current_score": 34,
      "live_win_rate": 0.00285,
      "top4_rate": 0.04903333333333333,
      "remaining_live_teams": 7,
      "p50_score": 114.0,
      "best_case_score": 319,
      "top3_rate": 0.03030000000000001,
      "top10_rate": 0.27146666666666663,
      "last_rate": 0.00095,
      "trend_rank_delta": -4.0,
      "trend_score_delta": 0.0,
      "trend_odds_delta": -0.031150000000000004,
      "trend_rank_direction": "down",
      "current_rank_label": 9,
      "teams": [
        {
          "team": "Purdue",
          "alive": true,
          "current_round_status": "not_played_current_round"
        },
        {
          "team": "Vanderbilt",
          "alive": true,
          "current_round_status": "not_played_current_round"
        },
        {
          "team": "Gonzaga",
          "alive": true,
          "current_round_status": "not_played_current_round"
        },
        {
          "team": "Wisconsin",
          "alive": false,
          "current_round_status": "eliminated_prior"
        },
        {
          "team": "Arkansas",
          "alive": true,
          "current_round_status": "not_played_current_round"
        },
        {
          "team": "Louisville",
          "alive": false,
          "current_round_status": "lost_current_round"
        },
        {
          "team": "UCLA",
          "alive": true,
          "current_round_status": "not_played_current_round"
        },
        {
          "team": "Tennessee",
          "alive": true,
          "current_round_status": "not_played_current_round"
        },
        {
          "team": "Iowa State",
          "alive": true,
          "current_round_status": "not_played_current_round"
        },
        {
          "team": "BYU",
          "alive": false,
          "current_round_status": "eliminated_prior"
        }
      ]
    },
    {
      "name": "Ryan Evans",
      "current_rank": 10,
      "current_score": 33,
      "live_win_rate": 0.043083333333333335,
      "top4_rate": 0.16314166666666666,
      "remaining_live_teams": 9,
      "p50_score": 108.0,
      "best_case_score": 281,
      "top3_rate": 0.1255166666666667,
      "top10_rate": 0.31685,
      "last_rate": 0.0036833333333333336,
      "trend_rank_delta": -3.0,
      "trend_score_delta": 0.0,
      "trend_odds_delta": -0.003316666666666662,
      "trend_rank_direction": "down",
      "current_rank_label": 10,
      "teams": [
        {
          "team": "Florida",
          "alive": true,
          "current_round_status": "not_played_current_round"
        },
        {
          "team": "Michigan",
          "alive": true,
          "current_round_status": "won_current_round"
        },
        {
          "team": "Kansas",
          "alive": true,
          "current_round_status": "not_played_current_round"
        },
        {
          "team": "Purdue",
          "alive": true,
          "current_round_status": "not_played_current_round"
        },
        {
          "team": "Texas Tech",
          "alive": true,
          "current_round_status": "not_played_current_round"
        },
        {
          "team": "South Florida",
          "alive": false,
          "current_round_status": "eliminated_prior"
        },
        {
          "team": "Texas",
          "alive": true,
          "current_round_status": "not_played_current_round"
        },
        {
          "team": "Arkansas",
          "alive": true,
          "current_round_status": "not_played_current_round"
        },
        {
          "team": "Illinois",
          "alive": true,
          "current_round_status": "not_played_current_round"
        },
        {
          "team": "Kentucky",
          "alive": true,
          "current_round_status": "not_played_current_round"
        }
      ]
    },
    {
      "name": "Sydney Taylor",
      "current_rank": 10,
      "current_score": 33,
      "live_win_rate": 0.025333333333333333,
      "top4_rate": 0.14979166666666666,
      "remaining_live_teams": 9,
      "p50_score": 120.0,
      "best_case_score": 320,
      "top3_rate": 0.10224166666666666,
      "top10_rate": 0.4405833333333334,
      "last_rate": 0.0010833333333333335,
      "trend_rank_delta": -3.0,
      "trend_score_delta": 0.0,
      "trend_odds_delta": 8.33333333333311e-05,
      "trend_rank_direction": "down",
      "current_rank_label": 10,
      "teams": [
        {
          "team": "Houston",
          "alive": true,
          "current_round_status": "not_played_current_round"
        },
        {
          "team": "Michigan",
          "alive": true,
          "current_round_status": "won_current_round"
        },
        {
          "team": "Iowa State",
          "alive": true,
          "current_round_status": "not_played_current_round"
        },
        {
          "team": "St. John's",
          "alive": true,
          "current_round_status": "not_played_current_round"
        },
        {
          "team": "Arkansas",
          "alive": true,
          "current_round_status": "not_played_current_round"
        },
        {
          "team": "Purdue",
          "alive": true,
          "current_round_status": "not_played_current_round"
        },
        {
          "team": "Vanderbilt",
          "alive": true,
          "current_round_status": "not_played_current_round"
        },
        {
          "team": "Tennessee",
          "alive": true,
          "current_round_status": "not_played_current_round"
        },
        {
          "team": "UCLA",
          "alive": true,
          "current_round_status": "not_played_current_round"
        },
        {
          "team": "BYU",
          "alive": false,
          "current_round_status": "eliminated_prior"
        }
      ]
    },
    {
      "name": "Sid Cash Jr.",
      "current_rank": 10,
      "current_score": 33,
      "live_win_rate": 0.0166,
      "top4_rate": 0.1270666666666667,
      "remaining_live_teams": 9,
      "p50_score": 119.0,
      "best_case_score": 336,
      "top3_rate": 0.08606666666666667,
      "top10_rate": 0.39430166666666666,
      "last_rate": 0.0011,
      "trend_rank_delta": -3.0,
      "trend_score_delta": 0.0,
      "trend_odds_delta": -0.003033333333333301,
      "trend_rank_direction": "down",
      "current_rank_label": 10,
      "teams": [
        {
          "team": "Arizona",
          "alive": true,
          "current_round_status": "not_played_current_round"
        },
        {
          "team": "Arkansas",
          "alive": true,
          "current_round_status": "not_played_current_round"
        },
        {
          "team": "Purdue",
          "alive": true,
          "current_round_status": "not_played_current_round"
        },
        {
          "team": "Tennessee",
          "alive": true,
          "current_round_status": "not_played_current_round"
        },
        {
          "team": "Texas Tech",
          "alive": true,
          "current_round_status": "not_played_current_round"
        },
        {
          "team": "South Florida",
          "alive": false,
          "current_round_status": "eliminated_prior"
        },
        {
          "team": "St. John's",
          "alive": true,
          "current_round_status": "not_played_current_round"
        },
        {
          "team": "UCLA",
          "alive": true,
          "current_round_status": "not_played_current_round"
        },
        {
          "team": "Houston",
          "alive": true,
          "current_round_status": "not_played_current_round"
        },
        {
          "team": "Vanderbilt",
          "alive": true,
          "current_round_status": "not_played_current_round"
        }
      ]
    },
    {
      "name": "Jack Anthony",
      "current_rank": 13,
      "current_score": 32,
      "live_win_rate": 0.00885,
      "top4_rate": 0.030533333333333332,
      "remaining_live_teams": 7,
      "p50_score": 83.0,
      "best_case_score": 290,
      "top3_rate": 0.023150000000000007,
      "top10_rate": 0.0825,
      "last_rate": 0.01803333333333334,
      "trend_rank_delta": 3.0,
      "trend_score_delta": 4.0,
      "trend_odds_delta": 0.0013166666666667003,
      "trend_rank_direction": "up",
      "current_rank_label": 13,
      "teams": [
        {
          "team": "Arkansas",
          "alive": true,
          "current_round_status": "not_played_current_round"
        },
        {
          "team": "St. John's",
          "alive": true,
          "current_round_status": "not_played_current_round"
        },
        {
          "team": "Michigan State",
          "alive": true,
          "current_round_status": "won_current_round"
        },
        {
          "team": "BYU",
          "alive": false,
          "current_round_status": "eliminated_prior"
        },
        {
          "team": "Texas A&M",
          "alive": true,
          "current_round_status": "not_played_current_round"
        },
        {
          "team": "TCU",
          "alive": true,
          "current_round_status": "not_played_current_round"
        },
        {
          "team": "Wisconsin",
          "alive": false,
          "current_round_status": "eliminated_prior"
        },
        {
          "team": "Iowa State",
          "alive": true,
          "current_round_status": "not_played_current_round"
        },
        {
          "team": "North Carolina",
          "alive": false,
          "current_round_status": "eliminated_prior"
        },
        {
          "team": "Vanderbilt",
          "alive": true,
          "current_round_status": "not_played_current_round"
        }
      ]
    },
    {
      "name": "John Fishback",
      "current_rank": 14,
      "current_score": 31,
      "live_win_rate": 0.04083333333333334,
      "top4_rate": 0.1580083333333333,
      "remaining_live_teams": 10,
      "p50_score": 109.0,
      "best_case_score": 245,
      "top3_rate": 0.12274166666666668,
      "top10_rate": 0.35517666666666664,
      "last_rate": 0.00225,
      "trend_rank_delta": 5.0,
      "trend_score_delta": 4.0,
      "trend_odds_delta": 0.002883333333333342,
      "trend_rank_direction": "up",
      "current_rank_label": 14,
      "teams": [
        {
          "team": "Florida",
          "alive": true,
          "current_round_status": "not_played_current_round"
        },
        {
          "team": "Michigan",
          "alive": true,
          "current_round_status": "won_current_round"
        },
        {
          "team": "Arizona",
          "alive": true,
          "current_round_status": "not_played_current_round"
        },
        {
          "team": "Iowa State",
          "alive": true,
          "current_round_status": "not_played_current_round"
        },
        {
          "team": "Illinois",
          "alive": true,
          "current_round_status": "not_played_current_round"
        },
        {
          "team": "Purdue",
          "alive": true,
          "current_round_status": "not_played_current_round"
        },
        {
          "team": "Michigan State",
          "alive": true,
          "current_round_status": "won_current_round"
        },
        {
          "team": "Nebraska",
          "alive": true,
          "current_round_status": "not_played_current_round"
        },
        {
          "team": "St. John's",
          "alive": true,
          "current_round_status": "not_played_current_round"
        },
        {
          "team": "UCLA",
          "alive": true,
          "current_round_status": "not_played_current_round"
        }
      ]
    },
    {
      "name": "Thomas Stephens",
      "current_rank": 14,
      "current_score": 31,
      "live_win_rate": 0.009683333333333334,
      "top4_rate": 0.07875,
      "remaining_live_teams": 9,
      "p50_score": 112.0,
      "best_case_score": 300,
      "top3_rate": 0.050275,
      "top10_rate": 0.303625,
      "last_rate": 8.333333333333333e-05,
      "trend_rank_delta": -3.0,
      "trend_score_delta": 0.0,
      "trend_odds_delta": -0.002966666666666666,
      "trend_rank_direction": "down",
      "current_rank_label": 14,
      "teams": [
        {
          "team": "Arizona",
          "alive": true,
          "current_round_status": "not_played_current_round"
        },
        {
          "team": "Houston",
          "alive": true,
          "current_round_status": "not_played_current_round"
        },
        {
          "team": "Illinois",
          "alive": true,
          "current_round_status": "not_played_current_round"
        },
        {
          "team": "Iowa State",
          "alive": true,
          "current_round_status": "not_played_current_round"
        },
        {
          "team": "Purdue",
          "alive": true,
          "current_round_status": "not_played_current_round"
        },
        {
          "team": "Arkansas",
          "alive": true,
          "current_round_status": "not_played_current_round"
        },
        {
          "team": "Vanderbilt",
          "alive": true,
          "current_round_status": "not_played_current_round"
        },
        {
          "team": "VCU",
          "alive": true,
          "current_round_status": "not_played_current_round"
        },
        {
          "team": "UCLA",
          "alive": true,
          "current_round_status": "not_played_current_round"
        },
        {
          "team": "Clemson",
          "alive": false,
          "current_round_status": "eliminated_prior"
        }
      ]
    },
    {
      "name": "Tanner Downs",
      "current_rank": 14,
      "current_score": 31,
      "live_win_rate": 0.0023333333333333335,
      "top4_rate": 0.06875,
      "remaining_live_teams": 8,
      "p50_score": 111.0,
      "best_case_score": 268,
      "top3_rate": 0.04388333333333334,
      "top10_rate": 0.24091666666666664,
      "last_rate": 0.00025,
      "trend_rank_delta": 5.0,
      "trend_score_delta": 4.0,
      "trend_odds_delta": 0.00048333333333333344,
      "trend_rank_direction": "up",
      "current_rank_label": 14,
      "teams": [
        {
          "team": "Arizona",
          "alive": true,
          "current_round_status": "not_played_current_round"
        },
        {
          "team": "Iowa State",
          "alive": true,
          "current_round_status": "not_played_current_round"
        },
        {
          "team": "Michigan State",
          "alive": true,
          "current_round_status": "won_current_round"
        },
        {
          "team": "Gonzaga",
          "alive": true,
          "current_round_status": "not_played_current_round"
        },
        {
          "team": "Arkansas",
          "alive": true,
          "current_round_status": "not_played_current_round"
        },
        {
          "team": "Purdue",
          "alive": true,
          "current_round_status": "not_played_current_round"
        },
        {
          "team": "Saint Mary's",
          "alive": false,
          "current_round_status": "eliminated_prior"
        },
        {
          "team": "Vanderbilt",
          "alive": true,
          "current_round_status": "not_played_current_round"
        },
        {
          "team": "BYU",
          "alive": false,
          "current_round_status": "eliminated_prior"
        },
        {
          "team": "Utah State",
          "alive": true,
          "current_round_status": "not_played_current_round"
        }
      ]
    },
    {
      "name": "Morgan Anthony",
      "current_rank": 17,
      "current_score": 30,
      "live_win_rate": 0.012233333333333332,
      "top4_rate": 0.06096666666666666,
      "remaining_live_teams": 7,
      "p50_score": 86.0,
      "best_case_score": 261,
      "top3_rate": 0.04591666666666667,
      "top10_rate": 0.15039166666666665,
      "last_rate": 0.0428,
      "trend_rank_delta": -3.0,
      "trend_score_delta": 0.0,
      "trend_odds_delta": -0.011466666666666667,
      "trend_rank_direction": "down",
      "current_rank_label": 17,
      "teams": [
        {
          "team": "Houston",
          "alive": true,
          "current_round_status": "not_played_current_round"
        },
        {
          "team": "Gonzaga",
          "alive": true,
          "current_round_status": "not_played_current_round"
        },
        {
          "team": "Tennessee",
          "alive": true,
          "current_round_status": "not_played_current_round"
        },
        {
          "team": "UConn",
          "alive": true,
          "current_round_status": "not_played_current_round"
        },
        {
          "team": "North Carolina",
          "alive": false,
          "current_round_status": "eliminated_prior"
        },
        {
          "team": "Vanderbilt",
          "alive": true,
          "current_round_status": "not_played_current_round"
        },
        {
          "team": "Louisville",
          "alive": false,
          "current_round_status": "lost_current_round"
        },
        {
          "team": "Ohio State",
          "alive": false,
          "current_round_status": "eliminated_prior"
        },
        {
          "team": "Iowa",
          "alive": true,
          "current_round_status": "not_played_current_round"
        },
        {
          "team": "St. John's",
          "alive": true,
          "current_round_status": "not_played_current_round"
        }
      ]
    },
    {
      "name": "Linda Cash",
      "current_rank": 17,
      "current_score": 30,
      "live_win_rate": 0.00975,
      "top4_rate": 0.041633333333333335,
      "remaining_live_teams": 9,
      "p50_score": 85.0,
      "best_case_score": 242,
      "top3_rate": 0.030616666666666667,
      "top10_rate": 0.11903333333333335,
      "last_rate": 0.01865,
      "trend_rank_delta": 7.0,
      "trend_score_delta": 4.0,
      "trend_odds_delta": 0.0016666666666667,
      "trend_rank_direction": "up",
      "current_rank_label": 17,
      "teams": [
        {
          "team": "Kansas",
          "alive": true,
          "current_round_status": "not_played_current_round"
        },
        {
          "team": "Michigan State",
          "alive": true,
          "current_round_status": "won_current_round"
        },
        {
          "team": "BYU",
          "alive": false,
          "current_round_status": "eliminated_prior"
        },
        {
          "team": "Arizona",
          "alive": true,
          "current_round_status": "not_played_current_round"
        },
        {
          "team": "Iowa State",
          "alive": true,
          "current_round_status": "not_played_current_round"
        },
        {
          "team": "Virginia",
          "alive": true,
          "current_round_status": "not_played_current_round"
        },
        {
          "team": "Texas Tech",
          "alive": true,
          "current_round_status": "not_played_current_round"
        },
        {
          "team": "Florida",
          "alive": true,
          "current_round_status": "not_played_current_round"
        },
        {
          "team": "Texas A&M",
          "alive": true,
          "current_round_status": "not_played_current_round"
        },
        {
          "team": "Vanderbilt",
          "alive": true,
          "current_round_status": "not_played_current_round"
        }
      ]
    },
    {
      "name": "Jack Reddeck",
      "current_rank": 17,
      "current_score": 30,
      "live_win_rate": 0.004466666666666667,
      "top4_rate": 0.0482,
      "remaining_live_teams": 8,
      "p50_score": 108.0,
      "best_case_score": 276,
      "top3_rate": 0.029375000000000005,
      "top10_rate": 0.21930999999999995,
      "last_rate": 0.0006833333333333334,
      "trend_rank_delta": 7.0,
      "trend_score_delta": 4.0,
      "trend_odds_delta": 0.0017666666666666673,
      "trend_rank_direction": "up",
      "current_rank_label": 17,
      "teams": [
        {
          "team": "Tennessee",
          "alive": true,
          "current_round_status": "not_played_current_round"
        },
        {
          "team": "Purdue",
          "alive": true,
          "current_round_status": "not_played_current_round"
        },
        {
          "team": "North Carolina",
          "alive": false,
          "current_round_status": "eliminated_prior"
        },
        {
          "team": "Iowa State",
          "alive": true,
          "current_round_status": "not_played_current_round"
        },
        {
          "team": "Arkansas",
          "alive": true,
          "current_round_status": "not_played_current_round"
        },
        {
          "team": "St. John's",
          "alive": true,
          "current_round_status": "not_played_current_round"
        },
        {
          "team": "Michigan State",
          "alive": true,
          "current_round_status": "won_current_round"
        },
        {
          "team": "BYU",
          "alive": false,
          "current_round_status": "eliminated_prior"
        },
        {
          "team": "Florida",
          "alive": true,
          "current_round_status": "not_played_current_round"
        },
        {
          "team": "Vanderbilt",
          "alive": true,
          "current_round_status": "not_played_current_round"
        }
      ]
    },
    {
      "name": "Ansley Duell",
      "current_rank": 17,
      "current_score": 30,
      "live_win_rate": 0.0037833333333333334,
      "top4_rate": 0.06047333333333332,
      "remaining_live_teams": 9,
      "p50_score": 106.0,
      "best_case_score": 259,
      "top3_rate": 0.03293666666666666,
      "top10_rate": 0.2587666666666666,
      "last_rate": 0.002725,
      "trend_rank_delta": 7.0,
      "trend_score_delta": 4.0,
      "trend_odds_delta": 0.0010333333333333336,
      "trend_rank_direction": "up",
      "current_rank_label": 17,
      "teams": [
        {
          "team": "Vanderbilt",
          "alive": true,
          "current_round_status": "not_played_current_round"
        },
        {
          "team": "Illinois",
          "alive": true,
          "current_round_status": "not_played_current_round"
        },
        {
          "team": "Duke",
          "alive": true,
          "current_round_status": "not_played_current_round"
        },
        {
          "team": "Michigan State",
          "alive": true,
          "current_round_status": "won_current_round"
        },
        {
          "team": "Wisconsin",
          "alive": false,
          "current_round_status": "eliminated_prior"
        },
        {
          "team": "Purdue",
          "alive": true,
          "current_round_status": "not_played_current_round"
        },
        {
          "team": "Michigan",
          "alive": true,
          "current_round_status": "won_current_round"
        },
        {
          "team": "Texas Tech",
          "alive": true,
          "current_round_status": "not_played_current_round"
        },
        {
          "team": "Iowa State",
          "alive": true,
          "current_round_status": "not_played_current_round"
        },
        {
          "team": "Kansas",
          "alive": true,
          "current_round_status": "not_played_current_round"
        }
      ]
    },
    {
      "name": "Jake Anthony",
      "current_rank": 21,
      "current_score": 29,
      "live_win_rate": 0.0,
      "top4_rate": 0.044274999999999995,
      "remaining_live_teams": 8,
      "p50_score": 113.0,
      "best_case_score": 314,
      "top3_rate": 0.0197,
      "top10_rate": 0.2734350000000001,
      "last_rate": 0.0015000000000000002,
      "trend_rank_delta": -6.0,
      "trend_score_delta": 0.0,
      "trend_odds_delta": 0.0,
      "trend_rank_direction": "down",
      "current_rank_label": 21,
      "teams": [
        {
          "team": "Arizona",
          "alive": true,
          "current_round_status": "not_played_current_round"
        },
        {
          "team": "Purdue",
          "alive": true,
          "current_round_status": "not_played_current_round"
        },
        {
          "team": "Vanderbilt",
          "alive": true,
          "current_round_status": "not_played_current_round"
        },
        {
          "team": "Tennessee",
          "alive": true,
          "current_round_status": "not_played_current_round"
        },
        {
          "team": "Arkansas",
          "alive": true,
          "current_round_status": "not_played_current_round"
        },
        {
          "team": "Iowa State",
          "alive": true,
          "current_round_status": "not_played_current_round"
        },
        {
          "team": "Illinois",
          "alive": true,
          "current_round_status": "not_played_current_round"
        },
        {
          "team": "BYU",
          "alive": false,
          "current_round_status": "eliminated_prior"
        },
        {
          "team": "UCLA",
          "alive": true,
          "current_round_status": "not_played_current_round"
        },
        {
          "team": "Ohio State",
          "alive": false,
          "current_round_status": "eliminated_prior"
        }
      ]
    },
    {
      "name": "Tim Dwyer",
      "current_rank": 22,
      "current_score": 28,
      "live_win_rate": 0.003633333333333333,
      "top4_rate": 0.03345,
      "remaining_live_teams": 8,
      "p50_score": 108.0,
      "best_case_score": 271,
      "top3_rate": 0.02025,
      "top10_rate": 0.2065166666666667,
      "last_rate": 0.00055,
      "trend_rank_delta": -6.0,
      "trend_score_delta": 0.0,
      "trend_odds_delta": -0.0004666666666666673,
      "trend_rank_direction": "down",
      "current_rank_label": 22,
      "teams": [
        {
          "team": "Wisconsin",
          "alive": false,
          "current_round_status": "eliminated_prior"
        },
        {
          "team": "South Florida",
          "alive": false,
          "current_round_status": "eliminated_prior"
        },
        {
          "team": "Arkansas",
          "alive": true,
          "current_round_status": "not_played_current_round"
        },
        {
          "team": "St. John's",
          "alive": true,
          "current_round_status": "not_played_current_round"
        },
        {
          "team": "Gonzaga",
          "alive": true,
          "current_round_status": "not_played_current_round"
        },
        {
          "team": "Purdue",
          "alive": true,
          "current_round_status": "not_played_current_round"
        },
        {
          "team": "Vanderbilt",
          "alive": true,
          "current_round_status": "not_played_current_round"
        },
        {
          "team": "Texas Tech",
          "alive": true,
          "current_round_status": "not_played_current_round"
        },
        {
          "team": "Iowa State",
          "alive": true,
          "current_round_status": "not_played_current_round"
        },
        {
          "team": "Kansas",
          "alive": true,
          "current_round_status": "not_played_current_round"
        }
      ]
    },
    {
      "name": "Liz Cuda",
      "current_rank": 22,
      "current_score": 28,
      "live_win_rate": 0.00175,
      "top4_rate": 0.0085,
      "remaining_live_teams": 6,
      "p50_score": 63.0,
      "best_case_score": 180,
      "top3_rate": 0.00535,
      "top10_rate": 0.03211666666666666,
      "last_rate": 0.11985,
      "trend_rank_delta": -6.0,
      "trend_score_delta": 0.0,
      "trend_odds_delta": -0.0038000000000000004,
      "trend_rank_direction": "down",
      "current_rank_label": 22,
      "teams": [
        {
          "team": "Virginia",
          "alive": true,
          "current_round_status": "not_played_current_round"
        },
        {
          "team": "Louisville",
          "alive": false,
          "current_round_status": "lost_current_round"
        },
        {
          "team": "High Point",
          "alive": true,
          "current_round_status": "not_played_current_round"
        },
        {
          "team": "Florida",
          "alive": true,
          "current_round_status": "not_played_current_round"
        },
        {
          "team": "North Carolina",
          "alive": false,
          "current_round_status": "eliminated_prior"
        },
        {
          "team": "Clemson",
          "alive": false,
          "current_round_status": "eliminated_prior"
        },
        {
          "team": "Iowa State",
          "alive": true,
          "current_round_status": "not_played_current_round"
        },
        {
          "team": "Gonzaga",
          "alive": true,
          "current_round_status": "not_played_current_round"
        },
        {
          "team": "St. John's",
          "alive": true,
          "current_round_status": "not_played_current_round"
        },
        {
          "team": "Saint Louis",
          "alive": false,
          "current_round_status": "lost_current_round"
        }
      ]
    },
    {
      "name": "MK Anthony",
      "current_rank": 24,
      "current_score": 27,
      "live_win_rate": 0.06185,
      "top4_rate": 0.17216666666666666,
      "remaining_live_teams": 10,
      "p50_score": 109.0,
      "best_case_score": 276,
      "top3_rate": 0.13671666666666665,
      "top10_rate": 0.34418999999999994,
      "last_rate": 0.004033333333333333,
      "trend_rank_delta": -5.0,
      "trend_score_delta": 0.0,
      "trend_odds_delta": -0.00026666666666659566,
      "trend_rank_direction": "down",
      "current_rank_label": 24,
      "teams": [
        {
          "team": "Duke",
          "alive": true,
          "current_round_status": "not_played_current_round"
        },
        {
          "team": "Houston",
          "alive": true,
          "current_round_status": "not_played_current_round"
        },
        {
          "team": "Arizona",
          "alive": true,
          "current_round_status": "not_played_current_round"
        },
        {
          "team": "Tennessee",
          "alive": true,
          "current_round_status": "not_played_current_round"
        },
        {
          "team": "Kansas",
          "alive": true,
          "current_round_status": "not_played_current_round"
        },
        {
          "team": "Nebraska",
          "alive": true,
          "current_round_status": "not_played_current_round"
        },
        {
          "team": "Arkansas",
          "alive": true,
          "current_round_status": "not_played_current_round"
        },
        {
          "team": "Purdue",
          "alive": true,
          "current_round_status": "not_played_current_round"
        },
        {
          "team": "Alabama",
          "alive": true,
          "current_round_status": "not_played_current_round"
        },
        {
          "team": "UConn",
          "alive": true,
          "current_round_status": "not_played_current_round"
        }
      ]
    },
    {
      "name": "Jimmy Anthony",
      "current_rank": 24,
      "current_score": 27,
      "live_win_rate": 0.026433333333333336,
      "top4_rate": 0.11094166666666667,
      "remaining_live_teams": 9,
      "p50_score": 93.0,
      "best_case_score": 239,
      "top3_rate": 0.08435,
      "top10_rate": 0.23801666666666665,
      "last_rate": 0.018533333333333336,
      "trend_rank_delta": -5.0,
      "trend_score_delta": 0.0,
      "trend_odds_delta": -0.006349999999999967,
      "trend_rank_direction": "down",
      "current_rank_label": 24,
      "teams": [
        {
          "team": "Michigan",
          "alive": true,
          "current_round_status": "won_current_round"
        },
        {
          "team": "Gonzaga",
          "alive": true,
          "current_round_status": "not_played_current_round"
        },
        {
          "team": "Arizona",
          "alive": true,
          "current_round_status": "not_played_current_round"
        },
        {
          "team": "Tennessee",
          "alive": true,
          "current_round_status": "not_played_current_round"
        },
        {
          "team": "Kentucky",
          "alive": true,
          "current_round_status": "not_played_current_round"
        },
        {
          "team": "Duke",
          "alive": true,
          "current_round_status": "not_played_current_round"
        },
        {
          "team": "Illinois",
          "alive": true,
          "current_round_status": "not_played_current_round"
        },
        {
          "team": "Nebraska",
          "alive": true,
          "current_round_status": "not_played_current_round"
        },
        {
          "team": "South Florida",
          "alive": false,
          "current_round_status": "eliminated_prior"
        },
        {
          "team": "Kansas",
          "alive": true,
          "current_round_status": "not_played_current_round"
        }
      ]
    },
    {
      "name": "Tyler Colson",
      "current_rank": 24,
      "current_score": 27,
      "live_win_rate": 0.007383333333333335,
      "top4_rate": 0.03788333333333333,
      "remaining_live_teams": 8,
      "p50_score": 91.0,
      "best_case_score": 198,
      "top3_rate": 0.0275,
      "top10_rate": 0.12070000000000003,
      "last_rate": 0.013291666666666669,
      "trend_rank_delta": 6.0,
      "trend_score_delta": 4.0,
      "trend_odds_delta": 0.0011333333333333343,
      "trend_rank_direction": "up",
      "current_rank_label": 24,
      "teams": [
        {
          "team": "Duke",
          "alive": true,
          "current_round_status": "not_played_current_round"
        },
        {
          "team": "Florida",
          "alive": true,
          "current_round_status": "not_played_current_round"
        },
        {
          "team": "Purdue",
          "alive": true,
          "current_round_status": "not_played_current_round"
        },
        {
          "team": "Iowa State",
          "alive": true,
          "current_round_status": "not_played_current_round"
        },
        {
          "team": "High Point",
          "alive": true,
          "current_round_status": "not_played_current_round"
        },
        {
          "team": "Michigan State",
          "alive": true,
          "current_round_status": "won_current_round"
        },
        {
          "team": "Arkansas",
          "alive": true,
          "current_round_status": "not_played_current_round"
        },
        {
          "team": "Alabama",
          "alive": true,
          "current_round_status": "not_played_current_round"
        },
        {
          "team": "BYU",
          "alive": false,
          "current_round_status": "eliminated_prior"
        },
        {
          "team": "Santa Clara",
          "alive": false,
          "current_round_status": "eliminated_prior"
        }
      ]
    },
    {
      "name": "Rob Blackwood",
      "current_rank": 24,
      "current_score": 27,
      "live_win_rate": 0.0024,
      "top4_rate": 0.01823333333333333,
      "remaining_live_teams": 7,
      "p50_score": 75.0,
      "best_case_score": 258,
      "top3_rate": 0.0137,
      "top10_rate": 0.049725000000000005,
      "last_rate": 0.03787499999999999,
      "trend_rank_delta": -5.0,
      "trend_score_delta": 0.0,
      "trend_odds_delta": -0.0006833333333333001,
      "trend_rank_direction": "down",
      "current_rank_label": 24,
      "teams": [
        {
          "team": "South Florida",
          "alive": false,
          "current_round_status": "eliminated_prior"
        },
        {
          "team": "UCF",
          "alive": false,
          "current_round_status": "eliminated_prior"
        },
        {
          "team": "Arkansas",
          "alive": true,
          "current_round_status": "not_played_current_round"
        },
        {
          "team": "Texas A&M",
          "alive": true,
          "current_round_status": "not_played_current_round"
        },
        {
          "team": "Vanderbilt",
          "alive": true,
          "current_round_status": "not_played_current_round"
        },
        {
          "team": "VCU",
          "alive": true,
          "current_round_status": "not_played_current_round"
        },
        {
          "team": "St. John's",
          "alive": true,
          "current_round_status": "not_played_current_round"
        },
        {
          "team": "BYU",
          "alive": false,
          "current_round_status": "eliminated_prior"
        },
        {
          "team": "Iowa State",
          "alive": true,
          "current_round_status": "not_played_current_round"
        },
        {
          "team": "Florida",
          "alive": true,
          "current_round_status": "not_played_current_round"
        }
      ]
    },
    {
      "name": "Caroline Colson",
      "current_rank": 28,
      "current_score": 26,
      "live_win_rate": 0.00635,
      "top4_rate": 0.05830833333333334,
      "remaining_live_teams": 9,
      "p50_score": 94.0,
      "best_case_score": 216,
      "top3_rate": 0.039383333333333326,
      "top10_rate": 0.19061666666666666,
      "last_rate": 0.0035,
      "trend_rank_delta": 6.0,
      "trend_score_delta": 4.0,
      "trend_odds_delta": 0.0022499999999999994,
      "trend_rank_direction": "up",
      "current_rank_label": 28,
      "teams": [
        {
          "team": "Florida",
          "alive": true,
          "current_round_status": "not_played_current_round"
        },
        {
          "team": "Duke",
          "alive": true,
          "current_round_status": "not_played_current_round"
        },
        {
          "team": "Michigan State",
          "alive": true,
          "current_round_status": "won_current_round"
        },
        {
          "team": "Iowa State",
          "alive": true,
          "current_round_status": "not_played_current_round"
        },
        {
          "team": "Texas Tech",
          "alive": true,
          "current_round_status": "not_played_current_round"
        },
        {
          "team": "Arkansas",
          "alive": true,
          "current_round_status": "not_played_current_round"
        },
        {
          "team": "Gonzaga",
          "alive": true,
          "current_round_status": "not_played_current_round"
        },
        {
          "team": "Missouri",
          "alive": false,
          "current_round_status": "eliminated_prior"
        },
        {
          "team": "Virginia",
          "alive": true,
          "current_round_status": "not_played_current_round"
        },
        {
          "team": "St. John's",
          "alive": true,
          "current_round_status": "not_played_current_round"
        }
      ]
    },
    {
      "name": "Morgan Fishback",
      "current_rank": 28,
      "current_score": 26,
      "live_win_rate": 0.0037,
      "top4_rate": 0.05106666666666667,
      "remaining_live_teams": 8,
      "p50_score": 90.0,
      "best_case_score": 284,
      "top3_rate": 0.030233333333333338,
      "top10_rate": 0.12845166666666663,
      "last_rate": 0.00295,
      "trend_rank_delta": -4.0,
      "trend_score_delta": 0.0,
      "trend_odds_delta": -0.0008999999999999998,
      "trend_rank_direction": "down",
      "current_rank_label": 28,
      "teams": [
        {
          "team": "South Florida",
          "alive": false,
          "current_round_status": "eliminated_prior"
        },
        {
          "team": "Vanderbilt",
          "alive": true,
          "current_round_status": "not_played_current_round"
        },
        {
          "team": "Arkansas",
          "alive": true,
          "current_round_status": "not_played_current_round"
        },
        {
          "team": "Iowa State",
          "alive": true,
          "current_round_status": "not_played_current_round"
        },
        {
          "team": "Saint Mary's",
          "alive": false,
          "current_round_status": "eliminated_prior"
        },
        {
          "team": "Illinois",
          "alive": true,
          "current_round_status": "not_played_current_round"
        },
        {
          "team": "Florida",
          "alive": true,
          "current_round_status": "not_played_current_round"
        },
        {
          "team": "St. John's",
          "alive": true,
          "current_round_status": "not_played_current_round"
        },
        {
          "team": "Texas",
          "alive": true,
          "current_round_status": "not_played_current_round"
        },
        {
          "team": "Michigan",
          "alive": true,
          "current_round_status": "won_current_round"
        }
      ]
    },
    {
      "name": "Bradley Duell",
      "current_rank": 30,
      "current_score": 24,
      "live_win_rate": 0.01765,
      "top4_rate": 0.08513333333333335,
      "remaining_live_teams": 9,
      "p50_score": 104.0,
      "best_case_score": 250,
      "top3_rate": 0.063,
      "top10_rate": 0.22029333333333329,
      "last_rate": 0.0017666666666666668,
      "trend_rank_delta": -2.0,
      "trend_score_delta": 0.0,
      "trend_odds_delta": -0.0021333333333332996,
      "trend_rank_direction": "down",
      "current_rank_label": 30,
      "teams": [
        {
          "team": "Arizona",
          "alive": true,
          "current_round_status": "not_played_current_round"
        },
        {
          "team": "Arkansas",
          "alive": true,
          "current_round_status": "not_played_current_round"
        },
        {
          "team": "Purdue",
          "alive": true,
          "current_round_status": "not_played_current_round"
        },
        {
          "team": "St. John's",
          "alive": true,
          "current_round_status": "not_played_current_round"
        },
        {
          "team": "UConn",
          "alive": true,
          "current_round_status": "not_played_current_round"
        },
        {
          "team": "Akron",
          "alive": false,
          "current_round_status": "eliminated_prior"
        },
        {
          "team": "Virginia",
          "alive": true,
          "current_round_status": "not_played_current_round"
        },
        {
          "team": "Houston",
          "alive": true,
          "current_round_status": "not_played_current_round"
        },
        {
          "team": "Vanderbilt",
          "alive": true,
          "current_round_status": "not_played_current_round"
        },
        {
          "team": "Illinois",
          "alive": true,
          "current_round_status": "not_played_current_round"
        }
      ]
    },
    {
      "name": "John Cash III",
      "current_rank": 30,
      "current_score": 24,
      "live_win_rate": 0.005083333333333333,
      "top4_rate": 0.04657333333333333,
      "remaining_live_teams": 9,
      "p50_score": 99.0,
      "best_case_score": 211,
      "top3_rate": 0.02937,
      "top10_rate": 0.19880166666666665,
      "last_rate": 0.004,
      "trend_rank_delta": 6.0,
      "trend_score_delta": 4.0,
      "trend_odds_delta": 0.000633333333333333,
      "trend_rank_direction": "up",
      "current_rank_label": 30,
      "teams": [
        {
          "team": "Florida",
          "alive": true,
          "current_round_status": "not_played_current_round"
        },
        {
          "team": "Arizona",
          "alive": true,
          "current_round_status": "not_played_current_round"
        },
        {
          "team": "Purdue",
          "alive": true,
          "current_round_status": "not_played_current_round"
        },
        {
          "team": "Wisconsin",
          "alive": false,
          "current_round_status": "eliminated_prior"
        },
        {
          "team": "Iowa State",
          "alive": true,
          "current_round_status": "not_played_current_round"
        },
        {
          "team": "Illinois",
          "alive": true,
          "current_round_status": "not_played_current_round"
        },
        {
          "team": "Michigan State",
          "alive": true,
          "current_round_status": "won_current_round"
        },
        {
          "team": "Duke",
          "alive": true,
          "current_round_status": "not_played_current_round"
        },
        {
          "team": "Gonzaga",
          "alive": true,
          "current_round_status": "not_played_current_round"
        },
        {
          "team": "Texas Tech",
          "alive": true,
          "current_round_status": "not_played_current_round"
        }
      ]
    },
    {
      "name": "Adam Harris",
      "current_rank": 30,
      "current_score": 24,
      "live_win_rate": 5e-05,
      "top4_rate": 0.007,
      "remaining_live_teams": 8,
      "p50_score": 79.0,
      "best_case_score": 218,
      "top3_rate": 0.003,
      "top10_rate": 0.050649999999999994,
      "last_rate": 0.026116666666666663,
      "trend_rank_delta": 6.0,
      "trend_score_delta": 4.0,
      "trend_odds_delta": -0.0002,
      "trend_rank_direction": "up",
      "current_rank_label": 30,
      "teams": [
        {
          "team": "St. John's",
          "alive": true,
          "current_round_status": "not_played_current_round"
        },
        {
          "team": "Wisconsin",
          "alive": false,
          "current_round_status": "eliminated_prior"
        },
        {
          "team": "Missouri",
          "alive": false,
          "current_round_status": "eliminated_prior"
        },
        {
          "team": "Texas Tech",
          "alive": true,
          "current_round_status": "not_played_current_round"
        },
        {
          "team": "Virginia",
          "alive": true,
          "current_round_status": "not_played_current_round"
        },
        {
          "team": "Vanderbilt",
          "alive": true,
          "current_round_status": "not_played_current_round"
        },
        {
          "team": "Illinois",
          "alive": true,
          "current_round_status": "not_played_current_round"
        },
        {
          "team": "Michigan State",
          "alive": true,
          "current_round_status": "won_current_round"
        },
        {
          "team": "Florida",
          "alive": true,
          "current_round_status": "not_played_current_round"
        },
        {
          "team": "Duke",
          "alive": true,
          "current_round_status": "not_played_current_round"
        }
      ]
    },
    {
      "name": "Bo Anthony",
      "current_rank": 30,
      "current_score": 24,
      "live_win_rate": 0.0,
      "top4_rate": 0.0034666666666666665,
      "remaining_live_teams": 6,
      "p50_score": 81.0,
      "best_case_score": 224,
      "top3_rate": 0.00125,
      "top10_rate": 0.032025,
      "last_rate": 0.04228333333333333,
      "trend_rank_delta": -2.0,
      "trend_score_delta": 0.0,
      "trend_odds_delta": -0.0054,
      "trend_rank_direction": "down",
      "current_rank_label": 30,
      "teams": [
        {
          "team": "Duke",
          "alive": true,
          "current_round_status": "not_played_current_round"
        },
        {
          "team": "Michigan",
          "alive": true,
          "current_round_status": "won_current_round"
        },
        {
          "team": "Vanderbilt",
          "alive": true,
          "current_round_status": "not_played_current_round"
        },
        {
          "team": "Arkansas",
          "alive": true,
          "current_round_status": "not_played_current_round"
        },
        {
          "team": "North Carolina",
          "alive": false,
          "current_round_status": "eliminated_prior"
        },
        {
          "team": "Clemson",
          "alive": false,
          "current_round_status": "eliminated_prior"
        },
        {
          "team": "Louisville",
          "alive": false,
          "current_round_status": "lost_current_round"
        },
        {
          "team": "Purdue",
          "alive": true,
          "current_round_status": "not_played_current_round"
        },
        {
          "team": "BYU",
          "alive": false,
          "current_round_status": "eliminated_prior"
        },
        {
          "team": "Virginia",
          "alive": true,
          "current_round_status": "not_played_current_round"
        }
      ]
    },
    {
      "name": "Dan Swatek",
      "current_rank": 34,
      "current_score": 23,
      "live_win_rate": 0.00575,
      "top4_rate": 0.05010833333333333,
      "remaining_live_teams": 9,
      "p50_score": 98.0,
      "best_case_score": 234,
      "top3_rate": 0.03175,
      "top10_rate": 0.19984666666666667,
      "last_rate": 0.0057,
      "trend_rank_delta": -4.0,
      "trend_score_delta": 0.0,
      "trend_odds_delta": 0.0008999999999999998,
      "trend_rank_direction": "down",
      "current_rank_label": 34,
      "teams": [
        {
          "team": "Arizona",
          "alive": true,
          "current_round_status": "not_played_current_round"
        },
        {
          "team": "Michigan",
          "alive": true,
          "current_round_status": "won_current_round"
        },
        {
          "team": "Duke",
          "alive": true,
          "current_round_status": "not_played_current_round"
        },
        {
          "team": "Florida",
          "alive": true,
          "current_round_status": "not_played_current_round"
        },
        {
          "team": "Kansas",
          "alive": true,
          "current_round_status": "not_played_current_round"
        },
        {
          "team": "Wisconsin",
          "alive": false,
          "current_round_status": "eliminated_prior"
        },
        {
          "team": "Tennessee",
          "alive": true,
          "current_round_status": "not_played_current_round"
        },
        {
          "team": "Purdue",
          "alive": true,
          "current_round_status": "not_played_current_round"
        },
        {
          "team": "Illinois",
          "alive": true,
          "current_round_status": "not_played_current_round"
        },
        {
          "team": "Gonzaga",
          "alive": true,
          "current_round_status": "not_played_current_round"
        }
      ]
    },
    {
      "name": "Luke Hurbanis",
      "current_rank": 34,
      "current_score": 23,
      "live_win_rate": 0.0025,
      "top4_rate": 0.0308,
      "remaining_live_teams": 9,
      "p50_score": 88.0,
      "best_case_score": 236,
      "top3_rate": 0.019766666666666665,
      "top10_rate": 0.12472333333333331,
      "last_rate": 0.0002,
      "trend_rank_delta": -4.0,
      "trend_score_delta": 0.0,
      "trend_odds_delta": -0.00115,
      "trend_rank_direction": "down",
      "current_rank_label": 34,
      "teams": [
        {
          "team": "Duke",
          "alive": true,
          "current_round_status": "not_played_current_round"
        },
        {
          "team": "Arizona",
          "alive": true,
          "current_round_status": "not_played_current_round"
        },
        {
          "team": "Michigan",
          "alive": true,
          "current_round_status": "won_current_round"
        },
        {
          "team": "Florida",
          "alive": true,
          "current_round_status": "not_played_current_round"
        },
        {
          "team": "UConn",
          "alive": true,
          "current_round_status": "not_played_current_round"
        },
        {
          "team": "Virginia",
          "alive": true,
          "current_round_status": "not_played_current_round"
        },
        {
          "team": "Arkansas",
          "alive": true,
          "current_round_status": "not_played_current_round"
        },
        {
          "team": "Texas Tech",
          "alive": true,
          "current_round_status": "not_played_current_round"
        },
        {
          "team": "Vanderbilt",
          "alive": true,
          "current_round_status": "not_played_current_round"
        },
        {
          "team": "Missouri",
          "alive": false,
          "current_round_status": "eliminated_prior"
        }
      ]
    },
    {
      "name": "Brant Fleming",
      "current_rank": 34,
      "current_score": 23,
      "live_win_rate": 0.0012333333333333335,
      "top4_rate": 0.01555,
      "remaining_live_teams": 8,
      "p50_score": 96.0,
      "best_case_score": 250,
      "top3_rate": 0.007766666666666667,
      "top10_rate": 0.106545,
      "last_rate": 0.008933333333333335,
      "trend_rank_delta": -4.0,
      "trend_score_delta": 0.0,
      "trend_odds_delta": -0.0007999999999999668,
      "trend_rank_direction": "down",
      "current_rank_label": 34,
      "teams": [
        {
          "team": "St. John's",
          "alive": true,
          "current_round_status": "not_played_current_round"
        },
        {
          "team": "Vanderbilt",
          "alive": true,
          "current_round_status": "not_played_current_round"
        },
        {
          "team": "Illinois",
          "alive": true,
          "current_round_status": "not_played_current_round"
        },
        {
          "team": "Arizona",
          "alive": true,
          "current_round_status": "not_played_current_round"
        },
        {
          "team": "Wisconsin",
          "alive": false,
          "current_round_status": "eliminated_prior"
        },
        {
          "team": "Purdue",
          "alive": true,
          "current_round_status": "not_played_current_round"
        },
        {
          "team": "Florida",
          "alive": true,
          "current_round_status": "not_played_current_round"
        },
        {
          "team": "Akron",
          "alive": false,
          "current_round_status": "eliminated_prior"
        },
        {
          "team": "Tennessee",
          "alive": true,
          "current_round_status": "not_played_current_round"
        },
        {
          "team": "Iowa State",
          "alive": true,
          "current_round_status": "not_played_current_round"
        }
      ]
    },
    {
      "name": "Lyles Downs",
      "current_rank": 37,
      "current_score": 21,
      "live_win_rate": 0.0001,
      "top4_rate": 0.00315,
      "remaining_live_teams": 6,
      "p50_score": 69.0,
      "best_case_score": 207,
      "top3_rate": 0.0014,
      "top10_rate": 0.040483333333333336,
      "last_rate": 0.09233333333333336,
      "trend_rank_delta": -2.0,
      "trend_score_delta": 0.0,
      "trend_odds_delta": 0.0,
      "trend_rank_direction": "down",
      "current_rank_label": 37,
      "teams": [
        {
          "team": "UConn",
          "alive": true,
          "current_round_status": "not_played_current_round"
        },
        {
          "team": "St. John's",
          "alive": true,
          "current_round_status": "not_played_current_round"
        },
        {
          "team": "Arkansas",
          "alive": true,
          "current_round_status": "not_played_current_round"
        },
        {
          "team": "Saint Mary's",
          "alive": false,
          "current_round_status": "eliminated_prior"
        },
        {
          "team": "Ohio State",
          "alive": false,
          "current_round_status": "eliminated_prior"
        },
        {
          "team": "McNeese",
          "alive": false,
          "current_round_status": "eliminated_prior"
        },
        {
          "team": "Villanova",
          "alive": false,
          "current_round_status": "eliminated_prior"
        },
        {
          "team": "UCLA",
          "alive": true,
          "current_round_status": "not_played_current_round"
        },
        {
          "team": "Gonzaga",
          "alive": true,
          "current_round_status": "not_played_current_round"
        },
        {
          "team": "Kansas",
          "alive": true,
          "current_round_status": "not_played_current_round"
        }
      ]
    },
    {
      "name": "Wade Cuda",
      "current_rank": 38,
      "current_score": 20,
      "live_win_rate": 0.002,
      "top4_rate": 0.02465,
      "remaining_live_teams": 7,
      "p50_score": 73.0,
      "best_case_score": 254,
      "top3_rate": 0.014983333333333331,
      "top10_rate": 0.06461666666666667,
      "last_rate": 0.07443333333333334,
      "trend_rank_delta": -2.0,
      "trend_score_delta": 0.0,
      "trend_odds_delta": -0.00018333333333330013,
      "trend_rank_direction": "down",
      "current_rank_label": 38,
      "teams": [
        {
          "team": "Florida",
          "alive": true,
          "current_round_status": "not_played_current_round"
        },
        {
          "team": "Duke",
          "alive": true,
          "current_round_status": "not_played_current_round"
        },
        {
          "team": "Arkansas",
          "alive": true,
          "current_round_status": "not_played_current_round"
        },
        {
          "team": "Missouri",
          "alive": false,
          "current_round_status": "eliminated_prior"
        },
        {
          "team": "Houston",
          "alive": true,
          "current_round_status": "not_played_current_round"
        },
        {
          "team": "Kentucky",
          "alive": true,
          "current_round_status": "not_played_current_round"
        },
        {
          "team": "BYU",
          "alive": false,
          "current_round_status": "eliminated_prior"
        },
        {
          "team": "Vanderbilt",
          "alive": true,
          "current_round_status": "not_played_current_round"
        },
        {
          "team": "South Florida",
          "alive": false,
          "current_round_status": "eliminated_prior"
        },
        {
          "team": "UConn",
          "alive": true,
          "current_round_status": "not_played_current_round"
        }
      ]
    },
    {
      "name": "Jimmy P",
      "current_rank": 38,
      "current_score": 20,
      "live_win_rate": 0.00195,
      "top4_rate": 0.01601666666666667,
      "remaining_live_teams": 7,
      "p50_score": 69.0,
      "best_case_score": 253,
      "top3_rate": 0.00845,
      "top10_rate": 0.0428,
      "last_rate": 0.12542499999999998,
      "trend_rank_delta": -2.0,
      "trend_score_delta": 0.0,
      "trend_odds_delta": 0.0004499999999999999,
      "trend_rank_direction": "down",
      "current_rank_label": 38,
      "teams": [
        {
          "team": "Florida",
          "alive": true,
          "current_round_status": "not_played_current_round"
        },
        {
          "team": "South Florida",
          "alive": false,
          "current_round_status": "eliminated_prior"
        },
        {
          "team": "Utah State",
          "alive": true,
          "current_round_status": "not_played_current_round"
        },
        {
          "team": "St. John's",
          "alive": true,
          "current_round_status": "not_played_current_round"
        },
        {
          "team": "Ohio State",
          "alive": false,
          "current_round_status": "eliminated_prior"
        },
        {
          "team": "Iowa State",
          "alive": true,
          "current_round_status": "not_played_current_round"
        },
        {
          "team": "Tennessee",
          "alive": true,
          "current_round_status": "not_played_current_round"
        },
        {
          "team": "Arizona",
          "alive": true,
          "current_round_status": "not_played_current_round"
        },
        {
          "team": "Wisconsin",
          "alive": false,
          "current_round_status": "eliminated_prior"
        },
        {
          "team": "Illinois",
          "alive": true,
          "current_round_status": "not_played_current_round"
        }
      ]
    },
    {
      "name": "Shelley Anthony",
      "current_rank": 40,
      "current_score": 19,
      "live_win_rate": 0.00245,
      "top4_rate": 0.021433333333333335,
      "remaining_live_teams": 8,
      "p50_score": 81.0,
      "best_case_score": 221,
      "top3_rate": 0.01465,
      "top10_rate": 0.07325833333333334,
      "last_rate": 0.021750000000000002,
      "trend_rank_delta": 0.0,
      "trend_score_delta": 0.0,
      "trend_odds_delta": 8.333333333340005e-05,
      "trend_rank_direction": "flat",
      "current_rank_label": 40,
      "teams": [
        {
          "team": "Arizona",
          "alive": true,
          "current_round_status": "not_played_current_round"
        },
        {
          "team": "Duke",
          "alive": true,
          "current_round_status": "not_played_current_round"
        },
        {
          "team": "Alabama",
          "alive": true,
          "current_round_status": "not_played_current_round"
        },
        {
          "team": "Virginia",
          "alive": true,
          "current_round_status": "not_played_current_round"
        },
        {
          "team": "Clemson",
          "alive": false,
          "current_round_status": "eliminated_prior"
        },
        {
          "team": "Vanderbilt",
          "alive": true,
          "current_round_status": "not_played_current_round"
        },
        {
          "team": "Illinois",
          "alive": true,
          "current_round_status": "not_played_current_round"
        },
        {
          "team": "BYU",
          "alive": false,
          "current_round_status": "eliminated_prior"
        },
        {
          "team": "Arkansas",
          "alive": true,
          "current_round_status": "not_played_current_round"
        },
        {
          "team": "Houston",
          "alive": true,
          "current_round_status": "not_played_current_round"
        }
      ]
    },
    {
      "name": "Gaines Cash",
      "current_rank": 41,
      "current_score": 16,
      "live_win_rate": 0.00065,
      "top4_rate": 0.0057,
      "remaining_live_teams": 7,
      "p50_score": 53.0,
      "best_case_score": 185,
      "top3_rate": 0.00335,
      "top10_rate": 0.019933333333333334,
      "last_rate": 0.29845,
      "trend_rank_delta": 0.0,
      "trend_score_delta": 0.0,
      "trend_odds_delta": -0.0006000000000000001,
      "trend_rank_direction": "flat",
      "current_rank_label": 41,
      "teams": [
        {
          "team": "Duke",
          "alive": true,
          "current_round_status": "not_played_current_round"
        },
        {
          "team": "UCF",
          "alive": false,
          "current_round_status": "eliminated_prior"
        },
        {
          "team": "UConn",
          "alive": true,
          "current_round_status": "not_played_current_round"
        },
        {
          "team": "Florida",
          "alive": true,
          "current_round_status": "not_played_current_round"
        },
        {
          "team": "Texas A&M",
          "alive": true,
          "current_round_status": "not_played_current_round"
        },
        {
          "team": "Virginia",
          "alive": true,
          "current_round_status": "not_played_current_round"
        },
        {
          "team": "Michigan",
          "alive": true,
          "current_round_status": "won_current_round"
        },
        {
          "team": "Arizona",
          "alive": true,
          "current_round_status": "not_played_current_round"
        },
        {
          "team": "BYU",
          "alive": false,
          "current_round_status": "eliminated_prior"
        },
        {
          "team": "Georgia",
          "alive": false,
          "current_round_status": "eliminated_prior"
        }
      ]
    }
  ]
}